language_toolkit/__init__.py
language_toolkit/filters/__init__.py
language_toolkit/filters/drain3.ini
language_toolkit/filters/labeling_function_collection.py
language_toolkit/filters/preprocessor_stack.py
language_toolkit/filters/string_filter.py
language_toolkit/filters/string_filtering.ipynb
language_toolkit/logger.py
language_toolkit/retrieval_augmented_generation/.dockerignore
language_toolkit/retrieval_augmented_generation/.gitignore
language_toolkit/retrieval_augmented_generation/__init__.py
language_toolkit/retrieval_augmented_generation/acronyms.csv
language_toolkit/retrieval_augmented_generation/config.toml
language_toolkit/retrieval_augmented_generation/docker-compose.yml
language_toolkit/retrieval_augmented_generation/environment.yml
language_toolkit/retrieval_augmented_generation/example_request.md
language_toolkit/retrieval_augmented_generation/filebeat.yml
language_toolkit/retrieval_augmented_generation/filebeatlogs.txt
language_toolkit/retrieval_augmented_generation/logstash.conf
language_toolkit/retrieval_augmented_generation/metricbeat.yml
language_toolkit/retrieval_augmented_generation/test.py
language_toolkit/retrieval_augmented_generation/utils/__init__.py
language_toolkit/retrieval_augmented_generation/utils/build_containers.py
language_toolkit/retrieval_augmented_generation/utils/run_containers.py
language_toolkit/retrieval_augmented_generation/utils/send_request.sh
language_toolkit/tests/__init__.py
language_toolkit/tests/collection_tests/__init__.py
language_toolkit/tests/collection_tests/test_labeling_function_collection.py
language_toolkit/tests/collection_tests/test_preprocessor_stack.py
language_toolkit/tests/data/SMSSpamCollection
language_toolkit/tests/data/test.csv
language_toolkit/tests/example_functions.py
language_toolkit/tests/pickled_models/label_model.pkl
language_toolkit/tests/pickled_models/mlp.pkl
language_toolkit/tests/pickled_models/random_forest.pkl
language_toolkit/tests/pickled_models/template_miner.pkl
language_toolkit-1.0.0.dist-info/LICENSE
language_toolkit-1.0.0.dist-info/METADATA
language_toolkit-1.0.0.dist-info/WHEEL
language_toolkit-1.0.0.dist-info/RECORD
